 { "endpoint": "mindforceimplants", "data":
[{"Id":21,"ItemId":5700021,"Name":"NeoPsion 85 Mindforce Implant","Properties":{"Description":null,"Weight":1,"MaxProfessionLevel":85,"Economy":{"MaxTT":175,"MinTT":null,"Absorption":0.02}},"Links":{"$Url":"/mindforceimplants/21"}},{"Id":24,"ItemId":5700024,"Name":"NeoPsion 100 Mindforce Implant","Properties":{"Description":null,"Weight":1,"MaxProfessionLevel":100,"Economy":{"MaxTT":200,"MinTT":null,"Absorption":0.02}},"Links":{"$Url":"/mindforceimplants/24"}},{"Id":25,"ItemId":5700025,"Name":"NeoPsion Mindforce Implant, Adjusted","Properties":{"Description":null,"Weight":1,"MaxProfessionLevel":110,"Economy":{"MaxTT":250,"MinTT":null,"Absorption":0.05}},"Links":{"$Url":"/mindforceimplants/25"}},{"Id":26,"ItemId":5700026,"Name":"NeoPsion Mindforce Implant, Augmented","Properties":{"Description":null,"Weight":1,"MaxProfessionLevel":140,"Economy":{"MaxTT":1200,"MinTT":null,"Absorption":0.3}},"Links":{"$Url":"/mindforceimplants/26"}},{"Id":27,"ItemId":5700027,"Name":"NeoPsion Mindforce Implant, Improved","Properties":{"Description":null,"Weight":1,"MaxProfessionLevel":120,"Economy":{"MaxTT":400,"MinTT":null,"Absorption":0.1}},"Links":{"$Url":"/mindforceimplants/27"}},{"Id":28,"ItemId":5700028,"Name":"NeoPsion Mindforce Implant, Modified","Properties":{"Description":null,"Weight":1,"MaxProfessionLevel":130,"Economy":{"MaxTT":800,"MinTT":null,"Absorption":0.2}},"Links":{"$Url":"/mindforceimplants/28"}},{"Id":29,"ItemId":5700029,"Name":"NeoPsion Mindforce Implant, Perfected","Properties":{"Description":null,"Weight":1,"MaxProfessionLevel":150,"Economy":{"MaxTT":1600,"MinTT":null,"Absorption":0.4}},"Links":{"$Url":"/mindforceimplants/29"}},{"Id":30,"ItemId":5700030,"Name":"NeoPsion Mindforce Implant, TWEN Edition","Properties":{"Description":null,"Weight":0.1,"MaxProfessionLevel":200,"Economy":{"MaxTT":1000,"MinTT":null,"Absorption":0.2}},"Links":{"$Url":"/mindforceimplants/30"}},{"Id":1,"ItemId":5700001,"Name":"NeoPsion 10-A Mindforce Implant (L)","Properties":{"Description":null,"Weight":1,"MaxProfessionLevel":10,"Economy":{"MaxTT":40,"MinTT":null,"Absorption":0.1}},"Links":{"$Url":"/mindforceimplants/1"}},{"Id":2,"ItemId":5700002,"Name":"NeoPsion 10-B Mindforce Implant (L)","Properties":{"Description":null,"Weight":1,"MaxProfessionLevel":10,"Economy":{"MaxTT":42,"MinTT":null,"Absorption":0.2}},"Links":{"$Url":"/mindforceimplants/2"}},{"Id":3,"ItemId":5700003,"Name":"NeoPsion 10 Mindforce Implant","Properties":{"Description":null,"Weight":1,"MaxProfessionLevel":10,"Economy":{"MaxTT":21.99,"MinTT":null,"Absorption":0.02}},"Links":{"$Url":"/mindforceimplants/3"}},{"Id":4,"ItemId":5700004,"Name":"NeoPsion 20-A Mindforce Implant (L)","Properties":{"Description":null,"Weight":1,"MaxProfessionLevel":20,"Economy":{"MaxTT":68,"MinTT":null,"Absorption":0.1}},"Links":{"$Url":"/mindforceimplants/4"}},{"Id":5,"ItemId":5700005,"Name":"NeoPsion 20-B Mindforce Implant (L)","Properties":{"Description":null,"Weight":1,"MaxProfessionLevel":20,"Economy":{"MaxTT":72,"MinTT":null,"Absorption":0.2}},"Links":{"$Url":"/mindforceimplants/5"}},{"Id":6,"ItemId":5700006,"Name":"NeoPsion 20 Mindforce Implant","Properties":{"Description":null,"Weight":1,"MaxProfessionLevel":20,"Economy":{"MaxTT":82,"MinTT":null,"Absorption":0.02}},"Links":{"$Url":"/mindforceimplants/6"}},{"Id":7,"ItemId":5700007,"Name":"NeoPsion 30-A Mindforce Implant (L)","Properties":{"Description":null,"Weight":1,"MaxProfessionLevel":30,"Economy":{"MaxTT":94,"MinTT":null,"Absorption":0.1}},"Links":{"$Url":"/mindforceimplants/7"}},{"Id":8,"ItemId":5700008,"Name":"NeoPsion 30-B Mindforce Implant (L)","Properties":{"Description":null,"Weight":1,"MaxProfessionLevel":30,"Economy":{"MaxTT":98,"MinTT":null,"Absorption":0.2}},"Links":{"$Url":"/mindforceimplants/8"}},{"Id":9,"ItemId":5700009,"Name":"NeoPsion 30 Mindforce Implant","Properties":{"Description":null,"Weight":1,"MaxProfessionLevel":30,"Economy":{"MaxTT":65,"MinTT":null,"Absorption":0.02}},"Links":{"$Url":"/mindforceimplants/9"}},{"Id":10,"ItemId":5700010,"Name":"NeoPsion 50-A Mindforce Implant (L)","Properties":{"Description":null,"Weight":1,"MaxProfessionLevel":50,"Economy":{"MaxTT":190,"MinTT":null,"Absorption":0.1}},"Links":{"$Url":"/mindforceimplants/10"}},{"Id":11,"ItemId":5700011,"Name":"NeoPsion 50-B Mindforce Implant (L)","Properties":{"Description":null,"Weight":1,"MaxProfessionLevel":50,"Economy":{"MaxTT":200,"MinTT":null,"Absorption":0.2}},"Links":{"$Url":"/mindforceimplants/11"}},{"Id":12,"ItemId":5700012,"Name":"NeoPsion 50 Mindforce Implant","Properties":{"Description":null,"Weight":1,"MaxProfessionLevel":50,"Economy":{"MaxTT":89,"MinTT":null,"Absorption":0.02}},"Links":{"$Url":"/mindforceimplants/12"}},{"Id":13,"ItemId":5700013,"Name":"NeoPsion 55-A Mindforce Implant (L)","Properties":{"Description":null,"Weight":1,"MaxProfessionLevel":55,"Economy":{"MaxTT":null,"MinTT":null,"Absorption":0.1}},"Links":{"$Url":"/mindforceimplants/13"}},{"Id":14,"ItemId":5700014,"Name":"NeoPsion 55-B Mindforce Implant (L)","Properties":{"Description":null,"Weight":1,"MaxProfessionLevel":55,"Economy":{"MaxTT":149,"MinTT":null,"Absorption":0.2}},"Links":{"$Url":"/mindforceimplants/14"}},{"Id":15,"ItemId":5700015,"Name":"NeoPsion 55 Mindforce Implant","Properties":{"Description":null,"Weight":1,"MaxProfessionLevel":55,"Economy":{"MaxTT":132,"MinTT":null,"Absorption":0.02}},"Links":{"$Url":"/mindforceimplants/15"}},{"Id":16,"ItemId":5700016,"Name":"NeoPsion 70-A Mindforce Implant (L)","Properties":{"Description":null,"Weight":1,"MaxProfessionLevel":70,"Economy":{"MaxTT":150,"MinTT":null,"Absorption":0.1}},"Links":{"$Url":"/mindforceimplants/16"}},{"Id":17,"ItemId":5700017,"Name":"NeoPsion 70-B Mindforce Implant (L)","Properties":{"Description":null,"Weight":1,"MaxProfessionLevel":70,"Economy":{"MaxTT":162,"MinTT":null,"Absorption":0.2}},"Links":{"$Url":"/mindforceimplants/17"}},{"Id":18,"ItemId":5700018,"Name":"NeoPsion 70 Mindforce Implant","Properties":{"Description":null,"Weight":1,"MaxProfessionLevel":70,"Economy":{"MaxTT":150,"MinTT":null,"Absorption":0.02}},"Links":{"$Url":"/mindforceimplants/18"}},{"Id":19,"ItemId":5700019,"Name":"NeoPsion 85-A Mindforce Implant (L)","Properties":{"Description":null,"Weight":1,"MaxProfessionLevel":85,"Economy":{"MaxTT":175,"MinTT":null,"Absorption":0.1}},"Links":{"$Url":"/mindforceimplants/19"}},{"Id":20,"ItemId":5700020,"Name":"NeoPsion 85-B Mindforce Implant (L)","Properties":{"Description":null,"Weight":1,"MaxProfessionLevel":85,"Economy":{"MaxTT":188,"MinTT":null,"Absorption":0.2}},"Links":{"$Url":"/mindforceimplants/20"}},{"Id":22,"ItemId":5700022,"Name":"NeoPsion 100-A Mindforce Implant (L)","Properties":{"Description":null,"Weight":1,"MaxProfessionLevel":100,"Economy":{"MaxTT":200,"MinTT":null,"Absorption":0.1}},"Links":{"$Url":"/mindforceimplants/22"}},{"Id":23,"ItemId":5700023,"Name":"NeoPsion 100-B Mindforce Implant (L)","Properties":{"Description":null,"Weight":1,"MaxProfessionLevel":100,"Economy":{"MaxTT":220,"MinTT":null,"Absorption":0.2}},"Links":{"$Url":"/mindforceimplants/23"}}]} 
